CHANGES.rst
LICENSE.txt
MANIFEST.in
README.rst
buildout.cfg
setup.py
src/j1m/__init__.py
src/j1m.ravenzconfig.egg-info/PKG-INFO
src/j1m.ravenzconfig.egg-info/SOURCES.txt
src/j1m.ravenzconfig.egg-info/dependency_links.txt
src/j1m.ravenzconfig.egg-info/entry_points.txt
src/j1m.ravenzconfig.egg-info/namespace_packages.txt
src/j1m.ravenzconfig.egg-info/not-zip-safe
src/j1m.ravenzconfig.egg-info/requires.txt
src/j1m.ravenzconfig.egg-info/top_level.txt
src/j1m/ravenzconfig/__init__.py
src/j1m/ravenzconfig/component.xml
src/j1m/ravenzconfig/tests.py