Metadata-Version: 1.1
Name: j1m.ravenzconfig
Version: 0.1.0
Summary: ZConfig logging support for raven
Home-page: https://github.com/jimfulton/j1m.ravenzconfig
Author: Jim Fulton
Author-email: jim@jimfulton.info
License: MIT
Keywords: raven,zconfig,sentry
Platform: UNKNOWN
Classifier: Intended Audience :: Developers
Classifier: License :: OSI Approved :: MIT License
Classifier: Programming Language :: Python
Classifier: Programming Language :: Python :: 2
Classifier: Programming Language :: Python :: 2.7
Classifier: Programming Language :: Python :: 3
Classifier: Programming Language :: Python :: 3.4
Classifier: Programming Language :: Python :: 3.5
Classifier: Programming Language :: Python :: 3.6
Classifier: Programming Language :: Python :: Implementation :: CPython
Classifier: Programming Language :: Python :: Implementation :: PyPy
Classifier: Topic :: Software Development :: Libraries :: Python Modules
Classifier: Operating System :: Microsoft :: Windows
Classifier: Operating System :: Unix
